{
    "products": [
        {
            "id": 263,
            "name": "Under Armour UA Spawn Low",
            "slug": "under-armour-ua-spawn-low",
            "short_desc": "Morbi purus libero, faucibus adipiscing, commodo quis, gravida id, est. Sed lectus. Praesent elementum hendrerit tortor. Sed semper lorem at felis. Vestibulum volutpat, lacus a ultrices sagittis, mi neque euismod dui, eu pulvinar nunc sapien ",
            "price": 77.99,
            "sale_price": null,
            "vendor": "demo24",
            "review": 2,
            "ratings": 5,
            "until": null,
            "stock": 100,
            "top": null,
            "featured": null,
            "new": null,
            "author": null,
            "sold": null,
            "created_by": {},
            "updated_by": {},
            "created_at": "2020-12-29T12:35:11.471Z",
            "updated_at": "2021-01-08T14:03:43.826Z",
            "variants": [],
            "pictures": [
                {
                    "id": 1344,
                    "name": "product-9-1.jpg",
                    "alternativeText": "",
                    "caption": "",
                    "width": 800,
                    "height": 800,
                    "formats": {},
                    "hash": "product_9_1_716ae2b67c",
                    "ext": ".jpg",
                    "mime": "image/jpeg",
                    "size": 33.99,
                    "url": "/db/uploads/product_9_1_716ae2b67c.jpg",
                    "previewUrl": null,
                    "provider": "local",
                    "provider_metadata": null,
                    "created_by": 4,
                    "updated_by": 4,
                    "created_at": "2020-12-29T12:25:48.288Z",
                    "updated_at": "2020-12-29T12:25:48.412Z"
                },
                {
                    "id": 1345,
                    "name": "product-9-2.jpg",
                    "alternativeText": "",
                    "caption": "",
                    "width": 800,
                    "height": 800,
                    "formats": {},
                    "hash": "product_9_2_f68d37ec0f",
                    "ext": ".jpg",
                    "mime": "image/jpeg",
                    "size": 24.56,
                    "url": "/db/uploads/product_9_2_f68d37ec0f.jpg",
                    "previewUrl": null,
                    "provider": "local",
                    "provider_metadata": null,
                    "created_by": 4,
                    "updated_by": 4,
                    "created_at": "2020-12-29T12:25:48.321Z",
                    "updated_at": "2020-12-29T12:25:48.449Z"
                },
                {
                    "id": 1347,
                    "name": "product-9-3.jpg",
                    "alternativeText": "",
                    "caption": "",
                    "width": 800,
                    "height": 800,
                    "formats": {},
                    "hash": "product_9_3_faf261ce08",
                    "ext": ".jpg",
                    "mime": "image/jpeg",
                    "size": 22.67,
                    "url": "/db/uploads/product_9_3_faf261ce08.jpg",
                    "previewUrl": null,
                    "provider": "local",
                    "provider_metadata": null,
                    "created_by": 4,
                    "updated_by": 4,
                    "created_at": "2020-12-29T12:25:48.369Z",
                    "updated_at": "2020-12-29T12:25:48.522Z"
                },
                {
                    "id": 1346,
                    "name": "product-9-4.jpg",
                    "alternativeText": "",
                    "caption": "",
                    "width": 800,
                    "height": 800,
                    "formats": {},
                    "hash": "product_9_4_44097bbea6",
                    "ext": ".jpg",
                    "mime": "image/jpeg",
                    "size": 15.97,
                    "url": "/db/uploads/product_9_4_44097bbea6.jpg",
                    "previewUrl": null,
                    "provider": "local",
                    "provider_metadata": null,
                    "created_by": 4,
                    "updated_by": 4,
                    "created_at": "2020-12-29T12:25:48.345Z",
                    "updated_at": "2020-12-29T12:25:48.489Z"
                }
            ],
            "sm_pictures": [
                {
                    "id": 1348,
                    "name": "product-9-1-300x300.jpg",
                    "alternativeText": "",
                    "caption": "",
                    "width": 300,
                    "height": 300,
                    "formats": {},
                    "hash": "product_9_1_300x300_629238c45e",
                    "ext": ".jpg",
                    "mime": "image/jpeg",
                    "size": 7.21,
                    "url": "/db/uploads/product_9_1_300x300_629238c45e.jpg",
                    "previewUrl": null,
                    "provider": "local",
                    "provider_metadata": null,
                    "created_by": 4,
                    "updated_by": 4,
                    "created_at": "2020-12-29T12:26:44.006Z",
                    "updated_at": "2020-12-29T12:26:44.121Z"
                },
                {
                    "id": 1350,
                    "name": "product-9-2-300x300.jpg",
                    "alternativeText": "",
                    "caption": "",
                    "width": 300,
                    "height": 300,
                    "formats": {},
                    "hash": "product_9_2_300x300_054faa87b4",
                    "ext": ".jpg",
                    "mime": "image/jpeg",
                    "size": 5.22,
                    "url": "/db/uploads/product_9_2_300x300_054faa87b4.jpg",
                    "previewUrl": null,
                    "provider": "local",
                    "provider_metadata": null,
                    "created_by": 4,
                    "updated_by": 4,
                    "created_at": "2020-12-29T12:26:44.060Z",
                    "updated_at": "2020-12-29T12:26:44.192Z"
                },
                {
                    "id": 1349,
                    "name": "product-9-3-300x300.jpg",
                    "alternativeText": "",
                    "caption": "",
                    "width": 300,
                    "height": 300,
                    "formats": {},
                    "hash": "product_9_3_300x300_6147b6af68",
                    "ext": ".jpg",
                    "mime": "image/jpeg",
                    "size": 4.72,
                    "url": "/db/uploads/product_9_3_300x300_6147b6af68.jpg",
                    "previewUrl": null,
                    "provider": "local",
                    "provider_metadata": null,
                    "created_by": 4,
                    "updated_by": 4,
                    "created_at": "2020-12-29T12:26:44.038Z",
                    "updated_at": "2020-12-29T12:26:44.157Z"
                },
                {
                    "id": 1351,
                    "name": "product-9-4-300x300.jpg",
                    "alternativeText": "",
                    "caption": "",
                    "width": 300,
                    "height": 300,
                    "formats": {},
                    "hash": "product_9_4_300x300_d126aae518",
                    "ext": ".jpg",
                    "mime": "image/jpeg",
                    "size": 3.23,
                    "url": "/db/uploads/product_9_4_300x300_d126aae518.jpg",
                    "previewUrl": null,
                    "provider": "local",
                    "provider_metadata": null,
                    "created_by": 4,
                    "updated_by": 4,
                    "created_at": "2020-12-29T12:26:44.079Z",
                    "updated_at": "2020-12-29T12:26:44.226Z"
                }
            ],
            "category": [
                {
                    "id": 3,
                    "name": "Camping",
                    "slug": "camping",
                    "created_by": null,
                    "updated_by": 4,
                    "created_at": "2020-03-14T10:25:39.408Z",
                    "updated_at": "2020-12-24T01:57:14.431Z"
                },
                {
                    "id": 2,
                    "name": "Men",
                    "slug": "men",
                    "created_by": null,
                    "updated_by": 4,
                    "created_at": "2020-03-14T10:25:21.611Z",
                    "updated_at": "2020-12-24T01:57:00.242Z"
                }
            ],
            "size": [
                {
                    "id": 1,
                    "name": "Largi",
                    "slug": "L"
                }
            ],
            "color": [
                {
                    "id": 2,
                    "name": "Grey",
                    "slug": "grey"
                }
            ],
            "brands": [
                {
                    "id": 19,
                    "name": "Nike",
                    "slug": "nike",
                    "created_by": 4,
                    "updated_by": 4,
                    "created_at": "2020-12-24T00:43:24.892Z",
                    "updated_at": "2020-12-24T00:43:24.907Z"
                },
                {
                    "id": 20,
                    "name": "F&F",
                    "slug": "fandf",
                    "created_by": 4,
                    "updated_by": 4,
                    "created_at": "2020-12-24T00:43:43.479Z",
                    "updated_at": "2020-12-24T00:43:43.499Z"
                }
            ]
        },
        {
            "id": 265,
            "name": "Snowboard Freestyle Italia - 135 cm",
            "slug": "snowboard-freestyle-italia",
            "short_desc": "Produs conceput pentru snowboarding. Ideal pentru copii între 1,45 m-1,60 m (nivel începător-mediu). 2 vârfuri pentru toleranţă la manevrare greşită şi practicare uşoară. Rază curbă mică pentru manevrabilitate în viraje. ",
            "price": 899,
            "sale_price": 849,
            "vendor": "demo24",
            "review": 2,
            "ratings": 5,
            "until": null,
            "stock": 100,
            "top": true,
            "featured": true,
            "new": false,
            "author": null,
            "sold": null,
            "created_by": {},
            "updated_by": {},
            "created_at": "2020-12-29T13:29:47.366Z",
            "updated_at": "2021-01-08T14:04:28.046Z",
            "variants": [],
            "pictures": [
                {
                    "id": 1360,
                    "name": "product-10-1.jpg",
                    "alternativeText": "",
                    "caption": "",
                    "width": 800,
                    "height": 800,
                    "formats": {},
                    "hash": "product_10_1_d8b95742e9",
                    "ext": ".jpg",
                    "mime": "image/jpeg",
                    "size": 25.89,
                    "url": "/db/uploads/product_10_1_d8b95742e9.jpg",
                    "previewUrl": null,
                    "provider": "local",
                    "provider_metadata": null,
                    "created_by": 4,
                    "updated_by": 4,
                    "created_at": "2020-12-29T13:27:42.812Z",
                    "updated_at": "2020-12-29T13:27:42.935Z"
                },
                {
                    "id": 1361,
                    "name": "product-10-2.jpg",
                    "alternativeText": "",
                    "caption": "",
                    "width": 800,
                    "height": 800,
                    "formats": {},
                    "hash": "product_10_2_3d9b9b0668",
                    "ext": ".jpg",
                    "mime": "image/jpeg",
                    "size": 29.11,
                    "url": "/db/uploads/product_10_2_3d9b9b0668.jpg",
                    "previewUrl": null,
                    "provider": "local",
                    "provider_metadata": null,
                    "created_by": 4,
                    "updated_by": 4,
                    "created_at": "2020-12-29T13:27:42.857Z",
                    "updated_at": "2020-12-29T13:27:42.964Z"
                },
                {
                    "id": 1363,
                    "name": "product-10-3.jpg",
                    "alternativeText": "",
                    "caption": "",
                    "width": 800,
                    "height": 800,
                    "formats": {},
                    "hash": "product_10_3_0df3c512a3",
                    "ext": ".jpg",
                    "mime": "image/jpeg",
                    "size": 25.39,
                    "url": "/db/uploads/product_10_3_0df3c512a3.jpg",
                    "previewUrl": null,
                    "provider": "local",
                    "provider_metadata": null,
                    "created_by": 4,
                    "updated_by": 4,
                    "created_at": "2020-12-29T13:27:42.899Z",
                    "updated_at": "2020-12-29T13:27:43.025Z"
                },
                {
                    "id": 1362,
                    "name": "product-10-4.jpg",
                    "alternativeText": "",
                    "caption": "",
                    "width": 800,
                    "height": 800,
                    "formats": {},
                    "hash": "product_10_4_a24254867c",
                    "ext": ".jpg",
                    "mime": "image/jpeg",
                    "size": 40.22,
                    "url": "/db/uploads/product_10_4_a24254867c.jpg",
                    "previewUrl": null,
                    "provider": "local",
                    "provider_metadata": null,
                    "created_by": 4,
                    "updated_by": 4,
                    "created_at": "2020-12-29T13:27:42.880Z",
                    "updated_at": "2020-12-29T13:27:42.994Z"
                }
            ],
            "sm_pictures": [
                {
                    "id": 1364,
                    "name": "product-2-1-300x300.jpg",
                    "alternativeText": "",
                    "caption": "",
                    "width": 300,
                    "height": 300,
                    "formats": {},
                    "hash": "product_2_1_300x300_3d60d8a3cf",
                    "ext": ".jpg",
                    "mime": "image/jpeg",
                    "size": 6.5,
                    "url": "/db/uploads/product_2_1_300x300_3d60d8a3cf.jpg",
                    "previewUrl": null,
                    "provider": "local",
                    "provider_metadata": null,
                    "created_by": 4,
                    "updated_by": 4,
                    "created_at": "2020-12-29T13:27:57.117Z",
                    "updated_at": "2020-12-29T13:27:57.247Z"
                },
                {
                    "id": 1365,
                    "name": "product-10-2-300x300.jpg",
                    "alternativeText": "",
                    "caption": "",
                    "width": 300,
                    "height": 300,
                    "formats": {},
                    "hash": "product_10_2_300x300_3a97dd2490",
                    "ext": ".jpg",
                    "mime": "image/jpeg",
                    "size": 6.07,
                    "url": "/db/uploads/product_10_2_300x300_3a97dd2490.jpg",
                    "previewUrl": null,
                    "provider": "local",
                    "provider_metadata": null,
                    "created_by": 4,
                    "updated_by": 4,
                    "created_at": "2020-12-29T13:27:57.147Z",
                    "updated_at": "2020-12-29T13:27:57.285Z"
                },
                {
                    "id": 1366,
                    "name": "product-10-3-300x300.jpg",
                    "alternativeText": "",
                    "caption": "",
                    "width": 300,
                    "height": 300,
                    "formats": {},
                    "hash": "product_10_3_300x300_708c425fc9",
                    "ext": ".jpg",
                    "mime": "image/jpeg",
                    "size": 6.08,
                    "url": "/db/uploads/product_10_3_300x300_708c425fc9.jpg",
                    "previewUrl": null,
                    "provider": "local",
                    "provider_metadata": null,
                    "created_by": 4,
                    "updated_by": 4,
                    "created_at": "2020-12-29T13:27:57.177Z",
                    "updated_at": "2020-12-29T13:27:57.318Z"
                },
                {
                    "id": 1367,
                    "name": "product-10-4-300x300.jpg",
                    "alternativeText": "",
                    "caption": "",
                    "width": 300,
                    "height": 300,
                    "formats": {},
                    "hash": "product_10_4_300x300_09febb738b",
                    "ext": ".jpg",
                    "mime": "image/jpeg",
                    "size": 8.88,
                    "url": "/db/uploads/product_10_4_300x300_09febb738b.jpg",
                    "previewUrl": null,
                    "provider": "local",
                    "provider_metadata": null,
                    "created_by": 4,
                    "updated_by": 4,
                    "created_at": "2020-12-29T13:27:57.207Z",
                    "updated_at": "2020-12-29T13:27:57.352Z"
                }
            ],
            "category": [
                {
                    "id": 6,
                    "name": "Sport",
                    "slug": "sport",
                    "created_by": null,
                    "updated_by": 4,
                    "created_at": "2020-03-14T10:26:39.769Z",
                    "updated_at": "2020-12-24T01:58:11.193Z"
                },
                {
                    "id": 1,
                    "name": "Women",
                    "slug": "women",
                    "created_by": null,
                    "updated_by": 4,
                    "created_at": "2020-03-14T10:24:42.894Z",
                    "updated_at": "2020-12-24T01:56:51.418Z"
                }
            ],
            "size": [
                {
                    "id": 3,
                    "name": "Mici",
                    "slug": "S"
                }
            ],
            "color": [
                {
                    "id": 4,
                    "name": "Brown",
                    "slug": "brown"
                }
            ],
            "brands": [
                {
                    "id": 19,
                    "name": "Drake",
                    "slug": "drake",
                    "created_by": 4,
                    "updated_by": 4,
                    "created_at": "2020-12-24T00:43:24.892Z",
                    "updated_at": "2020-12-24T00:43:24.907Z"
                }
            ]
        },
        {
            "id": 266,
            "name": "PUMA Ignite Limitless Leather",
            "slug": "puma-ignite-limitless-leather",
            "short_desc": "Morbi purus libero, faucibus adipiscing, commodo quis, gravida id, est. Sed lectus. Praesent elementum hendrerit tortor. Sed semper lorem at felis. Vestibulum volutpat, lacus a ultrices sagittis, mi neque euismod dui, eu pulvinar nunc sapien ornare nisl. Phasellus pede arcu, dapibus eu, ",
            "price": 52.66,
            "sale_price": null,
            "vendor": "demo24",
            "review": 2,
            "ratings": 3,
            "until": null,
            "stock": 100,
            "top": null,
            "featured": true,
            "new": null,
            "author": null,
            "sold": null,
            "created_by": {},
            "updated_by": {},
            "created_at": "2020-12-29T13:34:17.312Z",
            "updated_at": "2021-01-22T01:53:44.179Z",
            "variants": [],
            "pictures": [
                {
                    "id": 1369,
                    "name": "product-11-2.jpg",
                    "alternativeText": "",
                    "caption": "",
                    "width": 800,
                    "height": 800,
                    "formats": {},
                    "hash": "product_11_2_b0b16038fc",
                    "ext": ".jpg",
                    "mime": "image/jpeg",
                    "size": 25.24,
                    "url": "/db/uploads/product_11_2_b0b16038fc.jpg",
                    "previewUrl": null,
                    "provider": "local",
                    "provider_metadata": null,
                    "created_by": 4,
                    "updated_by": 4,
                    "created_at": "2020-12-29T13:31:46.945Z",
                    "updated_at": "2020-12-29T13:31:47.111Z"
                },
                {
                    "id": 1371,
                    "name": "product-11-3.jpg",
                    "alternativeText": "",
                    "caption": "",
                    "width": 800,
                    "height": 800,
                    "formats": {},
                    "hash": "product_11_3_26ac0fc233",
                    "ext": ".jpg",
                    "mime": "image/jpeg",
                    "size": 21.05,
                    "url": "/db/uploads/product_11_3_26ac0fc233.jpg",
                    "previewUrl": null,
                    "provider": "local",
                    "provider_metadata": null,
                    "created_by": 4,
                    "updated_by": 4,
                    "created_at": "2020-12-29T13:31:47.029Z",
                    "updated_at": "2020-12-29T13:31:47.186Z"
                },
                {
                    "id": 1370,
                    "name": "product-11-4.jpg",
                    "alternativeText": "",
                    "caption": "",
                    "width": 800,
                    "height": 800,
                    "formats": {},
                    "hash": "product_11_4_0a85f7ceb9",
                    "ext": ".jpg",
                    "mime": "image/jpeg",
                    "size": 14.72,
                    "url": "/db/uploads/product_11_4_0a85f7ceb9.jpg",
                    "previewUrl": null,
                    "provider": "local",
                    "provider_metadata": null,
                    "created_by": 4,
                    "updated_by": 4,
                    "created_at": "2020-12-29T13:31:47.008Z",
                    "updated_at": "2020-12-29T13:31:47.147Z"
                }
            ],
            "sm_pictures": [
                {
                    "id": 1372,
                    "name": "product-11-2-300x300.jpg",
                    "alternativeText": "",
                    "caption": "",
                    "width": 300,
                    "height": 300,
                    "formats": {},
                    "hash": "product_11_2_300x300_0c34205629",
                    "ext": ".jpg",
                    "mime": "image/jpeg",
                    "size": 5.84,
                    "url": "/db/uploads/product_11_2_300x300_0c34205629.jpg",
                    "previewUrl": null,
                    "provider": "local",
                    "provider_metadata": null,
                    "created_by": 4,
                    "updated_by": 4,
                    "created_at": "2020-12-29T13:32:32.201Z",
                    "updated_at": "2020-12-29T13:32:32.337Z"
                },
                {
                    "id": 1375,
                    "name": "product-11-3-300x300.jpg",
                    "alternativeText": "",
                    "caption": "",
                    "width": 800,
                    "height": 800,
                    "formats": {},
                    "hash": "product_11_3_300x300_846c50fe44",
                    "ext": ".jpg",
                    "mime": "image/jpeg",
                    "size": 21.05,
                    "url": "/db/uploads/product_11_3_300x300_846c50fe44.jpg",
                    "previewUrl": null,
                    "provider": "local",
                    "provider_metadata": null,
                    "created_by": 4,
                    "updated_by": 4,
                    "created_at": "2020-12-29T13:32:32.303Z",
                    "updated_at": "2020-12-29T13:32:32.445Z"
                },
                {
                    "id": 1373,
                    "name": "product-11-4-300x300.jpg",
                    "alternativeText": "",
                    "caption": "",
                    "width": 300,
                    "height": 300,
                    "formats": {},
                    "hash": "product_11_4_300x300_bf18aa438f",
                    "ext": ".jpg",
                    "mime": "image/jpeg",
                    "size": 3.02,
                    "url": "/db/uploads/product_11_4_300x300_bf18aa438f.jpg",
                    "previewUrl": null,
                    "provider": "local",
                    "provider_metadata": null,
                    "created_by": 4,
                    "updated_by": 4,
                    "created_at": "2020-12-29T13:32:32.242Z",
                    "updated_at": "2020-12-29T13:32:32.376Z"
                }
            ],
            "category": [
                {
                    "id": 2,
                    "name": "Men",
                    "slug": "men",
                    "created_by": null,
                    "updated_by": 4,
                    "created_at": "2020-03-14T10:25:21.611Z",
                    "updated_at": "2020-12-24T01:57:00.242Z"
                },
                {
                    "id": 3,
                    "name": "Sport",
                    "slug": "sport",
                    "created_by": null,
                    "updated_by": 4,
                    "created_at": "2020-03-14T10:25:39.408Z",
                    "updated_at": "2020-12-24T01:57:14.431Z"
                }
            ],
            "size": [
                {
                    "id": 5,
                    "name": "Medii",
                    "slug": "M"
                }
            ],
            "color": [
                {
                    "id": 6,
                    "name": "Blue",
                    "slug": "blue"
                }
            ],
            "brands": [
                {
                    "id": 19,
                    "name": "Raven",
                    "slug": "raven",
                    "created_by": 4,
                    "updated_by": 4,
                    "created_at": "2020-12-24T00:43:24.892Z",
                    "updated_at": "2020-12-24T00:43:24.907Z"
                }
            ]
        },
        {
            "id": 267,
            "name": "Small Sleeping Bag",
            "slug": "small-sleeping-bag",
            "short_desc": "Morbi purus libero, faucibus adipiscing, commodo quis, gravida id, est. Sed lectus. Praesent elementum hendrerit tortor. Sed semper lorem at felis. Vestibulum volutpat, lacus a ultrices sagittis, mi neque euismod dui, eu pulvinar nunc sapien ornare nisl. Phasellus pede arcu, dapibus eu, ",
            "price": 299.99,
            "sale_price": null,
            "vendor": "demo24",
            "review": 2,
            "ratings": 5,
            "until": null,
            "stock": 100,
            "top": true,
            "featured": true,
            "new": null,
            "author": null,
            "sold": null,
            "created_by": {},
            "updated_by": {},
            "created_at": "2020-12-29T13:37:17.348Z",
            "updated_at": "2021-01-21T13:51:17.344Z",
            "variants": [],
            "pictures": [
                {
                    "id": 1377,
                    "name": "product-12-1.jpg",
                    "alternativeText": "",
                    "caption": "",
                    "width": 800,
                    "height": 800,
                    "formats": {},
                    "hash": "product_12_1_fbd7c7de0b",
                    "ext": ".jpg",
                    "mime": "image/jpeg",
                    "size": 28.49,
                    "url": "/db/uploads/product_12_1_fbd7c7de0b.jpg",
                    "previewUrl": null,
                    "provider": "local",
                    "provider_metadata": null,
                    "created_by": 4,
                    "updated_by": 4,
                    "created_at": "2020-12-29T13:35:00.064Z",
                    "updated_at": "2020-12-29T13:35:00.134Z"
                },
                {
                    "id": 1376,
                    "name": "product-12-2.jpg",
                    "alternativeText": "",
                    "caption": "",
                    "width": 800,
                    "height": 800,
                    "formats": {},
                    "hash": "product_12_2_abce1bb3d6",
                    "ext": ".jpg",
                    "mime": "image/jpeg",
                    "size": 24.05,
                    "url": "/db/uploads/product_12_2_abce1bb3d6.jpg",
                    "previewUrl": null,
                    "provider": "local",
                    "provider_metadata": null,
                    "created_by": 4,
                    "updated_by": 4,
                    "created_at": "2020-12-29T13:35:00.036Z",
                    "updated_at": "2020-12-29T13:35:00.101Z"
                }
            ],
            "sm_pictures": [
                {
                    "id": 1378,
                    "name": "product-12-1-300x300.jpg",
                    "alternativeText": "",
                    "caption": "",
                    "width": 300,
                    "height": 300,
                    "formats": {},
                    "hash": "product_12_1_300x300_53d52a433a",
                    "ext": ".jpg",
                    "mime": "image/jpeg",
                    "size": 5.97,
                    "url": "/db/uploads/product_12_1_300x300_53d52a433a.jpg",
                    "previewUrl": null,
                    "provider": "local",
                    "provider_metadata": null,
                    "created_by": 4,
                    "updated_by": 4,
                    "created_at": "2020-12-29T13:35:12.031Z",
                    "updated_at": "2020-12-29T13:35:12.092Z"
                },
                {
                    "id": 1379,
                    "name": "product-12-2-300x300.jpg",
                    "alternativeText": "",
                    "caption": "",
                    "width": 300,
                    "height": 300,
                    "formats": {},
                    "hash": "product_12_2_300x300_6f31645898",
                    "ext": ".jpg",
                    "mime": "image/jpeg",
                    "size": 4.99,
                    "url": "/db/uploads/product_12_2_300x300_6f31645898.jpg",
                    "previewUrl": null,
                    "provider": "local",
                    "provider_metadata": null,
                    "created_by": 4,
                    "updated_by": 4,
                    "created_at": "2020-12-29T13:35:12.058Z",
                    "updated_at": "2020-12-29T13:35:12.123Z"
                }
            ],
            "category": [
                {
                    "id": 18,
                    "name": "Accessories",
                    "slug": "accessories",
                    "created_by": 4,
                    "updated_by": 4,
                    "created_at": "2020-12-24T03:48:30.273Z",
                    "updated_at": "2020-12-24T03:48:30.347Z"
                },
                {
                    "id": 6,
                    "name": "Bags",
                    "slug": "bags",
                    "created_by": null,
                    "updated_by": 4,
                    "created_at": "2020-03-14T10:26:39.769Z",
                    "updated_at": "2020-12-24T01:58:11.193Z"
                },
                {
                    "id": 1,
                    "name": "Women",
                    "slug": "women",
                    "created_by": null,
                    "updated_by": 4,
                    "created_at": "2020-03-14T10:24:42.894Z",
                    "updated_at": "2020-12-24T01:56:51.418Z"
                }
            ],
            "size": [
                {
                    "id": 1,
                    "name": "Largi",
                    "slug": "L"
                }
            ],
            "color": [
                {
                    "id": 2,
                    "name": "Grey",
                    "slug": "grey"
                }
            ],
            "brands": [
                {
                    "id": 19,
                    "name": "Nike",
                    "slug": "nike",
                    "created_by": 4,
                    "updated_by": 4,
                    "created_at": "2020-12-24T00:43:24.892Z",
                    "updated_at": "2020-12-24T00:43:24.907Z"
                }
            ]
        },
        {
            "id": 268,
            "name": "Alphaskin Sport Bra",
            "slug": "alphaskin-sport-bra",
            "short_desc": "Morbi purus libero, faucibus adipiscing, commodo quis, gravida id, est. Sed lectus. Praesent elementum hendrerit tortor. Sed semper lorem at felis. Vestibulum volutpat, lacus a ultrices sagittis, mi neque euismod dui, eu pulvinar nunc sapien ornare nisl. Phasellus pede arcu, dapibus eu, ",
            "price": 34.99,
            "sale_price": null,
            "vendor": "demo24",
            "review": 2,
            "ratings": 5,
            "until": null,
            "stock": 100,
            "top": null,
            "featured": true,
            "new": null,
            "author": null,
            "sold": null,
            "created_by": {},
            "updated_by": {},
            "created_at": "2020-12-29T13:44:16.305Z",
            "updated_at": "2021-01-08T14:05:21.015Z",
            "variants": [],
            "pictures": [
                {
                    "id": 1380,
                    "name": "product-13-1.jpg",
                    "alternativeText": "",
                    "caption": "",
                    "width": 800,
                    "height": 800,
                    "formats": {},
                    "hash": "product_13_1_355d0c9476",
                    "ext": ".jpg",
                    "mime": "image/jpeg",
                    "size": 27.6,
                    "url": "/db/uploads/product_13_1_355d0c9476.jpg",
                    "previewUrl": null,
                    "provider": "local",
                    "provider_metadata": null,
                    "created_by": 4,
                    "updated_by": 4,
                    "created_at": "2020-12-29T13:38:29.876Z",
                    "updated_at": "2020-12-29T13:38:30.028Z"
                },
                {
                    "id": 1381,
                    "name": "product-13-2.jpg",
                    "alternativeText": "",
                    "caption": "",
                    "width": 800,
                    "height": 800,
                    "formats": {},
                    "hash": "product_13_2_ce2358f91a",
                    "ext": ".jpg",
                    "mime": "image/jpeg",
                    "size": 34.59,
                    "url": "/db/uploads/product_13_2_ce2358f91a.jpg",
                    "previewUrl": null,
                    "provider": "local",
                    "provider_metadata": null,
                    "created_by": 4,
                    "updated_by": 4,
                    "created_at": "2020-12-29T13:38:29.939Z",
                    "updated_at": "2020-12-29T13:38:30.059Z"
                },
                {
                    "id": 1383,
                    "name": "product-13-3.jpg",
                    "alternativeText": "",
                    "caption": "",
                    "width": 800,
                    "height": 800,
                    "formats": {},
                    "hash": "product_13_3_726bb7f0cc",
                    "ext": ".jpg",
                    "mime": "image/jpeg",
                    "size": 106.17,
                    "url": "/db/uploads/product_13_3_726bb7f0cc.jpg",
                    "previewUrl": null,
                    "provider": "local",
                    "provider_metadata": null,
                    "created_by": 4,
                    "updated_by": 4,
                    "created_at": "2020-12-29T13:38:29.981Z",
                    "updated_at": "2020-12-29T13:38:30.134Z"
                },
                {
                    "id": 1382,
                    "name": "product-13-4.jpg",
                    "alternativeText": "",
                    "caption": "",
                    "width": 800,
                    "height": 800,
                    "formats": {},
                    "hash": "product_13_4_64b0a5ad60",
                    "ext": ".jpg",
                    "mime": "image/jpeg",
                    "size": 127.09,
                    "url": "/db/uploads/product_13_4_64b0a5ad60.jpg",
                    "previewUrl": null,
                    "provider": "local",
                    "provider_metadata": null,
                    "created_by": 4,
                    "updated_by": 4,
                    "created_at": "2020-12-29T13:38:29.959Z",
                    "updated_at": "2020-12-29T13:38:30.096Z"
                }
            ],
            "sm_pictures": [
                {
                    "id": 1384,
                    "name": "product-13-1-300x300.jpg",
                    "alternativeText": "",
                    "caption": "",
                    "width": 300,
                    "height": 300,
                    "formats": {},
                    "hash": "product_13_1_300x300_20f0f8a704",
                    "ext": ".jpg",
                    "mime": "image/jpeg",
                    "size": 5.84,
                    "url": "/db/uploads/product_13_1_300x300_20f0f8a704.jpg",
                    "previewUrl": null,
                    "provider": "local",
                    "provider_metadata": null,
                    "created_by": 4,
                    "updated_by": 4,
                    "created_at": "2020-12-29T13:38:54.718Z",
                    "updated_at": "2020-12-29T13:38:54.839Z"
                },
                {
                    "id": 1385,
                    "name": "product-13-2-300x300.jpg",
                    "alternativeText": "",
                    "caption": "",
                    "width": 300,
                    "height": 300,
                    "formats": {},
                    "hash": "product_13_2_300x300_2f860089d9",
                    "ext": ".jpg",
                    "mime": "image/jpeg",
                    "size": 6.54,
                    "url": "/db/uploads/product_13_2_300x300_2f860089d9.jpg",
                    "previewUrl": null,
                    "provider": "local",
                    "provider_metadata": null,
                    "created_by": 4,
                    "updated_by": 4,
                    "created_at": "2020-12-29T13:38:54.744Z",
                    "updated_at": "2020-12-29T13:38:54.880Z"
                },
                {
                    "id": 1386,
                    "name": "product-13-3-300x300.jpg",
                    "alternativeText": "",
                    "caption": "",
                    "width": 300,
                    "height": 300,
                    "formats": {},
                    "hash": "product_13_3_300x300_345dfeb2c9",
                    "ext": ".jpg",
                    "mime": "image/jpeg",
                    "size": 14.97,
                    "url": "/db/uploads/product_13_3_300x300_345dfeb2c9.jpg",
                    "previewUrl": null,
                    "provider": "local",
                    "provider_metadata": null,
                    "created_by": 4,
                    "updated_by": 4,
                    "created_at": "2020-12-29T13:38:54.770Z",
                    "updated_at": "2020-12-29T13:38:54.913Z"
                },
                {
                    "id": 1387,
                    "name": "product-13-4-300x300.jpg",
                    "alternativeText": "",
                    "caption": "",
                    "width": 300,
                    "height": 300,
                    "formats": {},
                    "hash": "product_13_4_300x300_324f2ab7e4",
                    "ext": ".jpg",
                    "mime": "image/jpeg",
                    "size": 23.18,
                    "url": "/db/uploads/product_13_4_300x300_324f2ab7e4.jpg",
                    "previewUrl": null,
                    "provider": "local",
                    "provider_metadata": null,
                    "created_by": 4,
                    "updated_by": 4,
                    "created_at": "2020-12-29T13:38:54.796Z",
                    "updated_at": "2020-12-29T13:38:54.949Z"
                }
            ],
            "category": [
                {
                    "id": 72,
                    "name": "Tops",
                    "slug": "tops",
                    "created_by": 4,
                    "updated_by": 4,
                    "created_at": "2020-12-24T04:42:44.850Z",
                    "updated_at": "2020-12-24T04:42:44.865Z"
                },
                {
                    "id": 1,
                    "name": "Women",
                    "slug": "women",
                    "created_by": null,
                    "updated_by": 4,
                    "created_at": "2020-03-14T10:24:42.894Z",
                    "updated_at": "2020-12-24T01:56:51.418Z"
                }
            ],
            "size": [
                {
                    "id": 1,
                    "name": "Largi",
                    "slug": "L"
                }
            ],
            "color": [
                {
                    "id": 2,
                    "name": "Grey",
                    "slug": "grey"
                }
            ],
            "brands": [
                {
                    "id": 19,
                    "name": "Nike",
                    "slug": "nike",
                    "created_by": 4,
                    "updated_by": 4,
                    "created_at": "2020-12-24T00:43:24.892Z",
                    "updated_at": "2020-12-24T00:43:24.907Z"
                }
            ]
        },
        {
            "id": 269,
            "name": "Watertight Jacket",
            "slug": "watertight-jacket",
            "short_desc": "Morbi purus libero, faucibus adipiscing, commodo quis, gravida id, est. Sed lectus. Praesent elementum hendrerit tortor. Sed semper lorem at felis. Vestibulum volutpat, lacus a ultrices sagittis, mi neque euismod dui, eu pulvinar nunc sapien ornare nisl. Phasellus pede arcu, dapibus eu, ",
            "price": 76.99,
            "sale_price": null,
            "vendor": "demo24",
            "review": 2,
            "ratings": 4,
            "until": null,
            "stock": 100,
            "top": true,
            "featured": true,
            "new": null,
            "author": null,
            "sold": null,
            "created_by": {},
            "updated_by": {},
            "created_at": "2020-12-29T13:47:13.438Z",
            "updated_at": "2021-01-21T13:52:34.418Z",
            "variants": [],
            "pictures": [
                {
                    "id": 1388,
                    "name": "product-14-2.jpg",
                    "alternativeText": "",
                    "caption": "",
                    "width": 800,
                    "height": 800,
                    "formats": {},
                    "hash": "product_14_2_3c46b8ac48",
                    "ext": ".jpg",
                    "mime": "image/jpeg",
                    "size": 32.45,
                    "url": "/db/uploads/product_14_2_3c46b8ac48.jpg",
                    "previewUrl": null,
                    "provider": "local",
                    "provider_metadata": null,
                    "created_by": 4,
                    "updated_by": 4,
                    "created_at": "2020-12-29T13:45:57.107Z",
                    "updated_at": "2020-12-29T13:45:57.194Z"
                },
                {
                    "id": 1389,
                    "name": "product-14-1.jpg",
                    "alternativeText": "",
                    "caption": "",
                    "width": 800,
                    "height": 800,
                    "formats": {},
                    "hash": "product_14_1_ab853a5304",
                    "ext": ".jpg",
                    "mime": "image/jpeg",
                    "size": 29.69,
                    "url": "/db/uploads/product_14_1_ab853a5304.jpg",
                    "previewUrl": null,
                    "provider": "local",
                    "provider_metadata": null,
                    "created_by": 4,
                    "updated_by": 4,
                    "created_at": "2020-12-29T13:45:57.138Z",
                    "updated_at": "2020-12-29T13:45:57.229Z"
                },
                {
                    "id": 1390,
                    "name": "product-14-3.jpg",
                    "alternativeText": "",
                    "caption": "",
                    "width": 800,
                    "height": 800,
                    "formats": {},
                    "hash": "product_14_3_6e9718896c",
                    "ext": ".jpg",
                    "mime": "image/jpeg",
                    "size": 24.07,
                    "url": "/db/uploads/product_14_3_6e9718896c.jpg",
                    "previewUrl": null,
                    "provider": "local",
                    "provider_metadata": null,
                    "created_by": 4,
                    "updated_by": 4,
                    "created_at": "2020-12-29T13:45:57.160Z",
                    "updated_at": "2020-12-29T13:45:57.264Z"
                }
            ],
            "sm_pictures": [
                {
                    "id": 1391,
                    "name": "product-14-2-300x300.jpg",
                    "alternativeText": "",
                    "caption": "",
                    "width": 300,
                    "height": 300,
                    "formats": {},
                    "hash": "product_14_2_300x300_7294a7fb72",
                    "ext": ".jpg",
                    "mime": "image/jpeg",
                    "size": 8.23,
                    "url": "/db/uploads/product_14_2_300x300_7294a7fb72.jpg",
                    "previewUrl": null,
                    "provider": "local",
                    "provider_metadata": null,
                    "created_by": 4,
                    "updated_by": 4,
                    "created_at": "2020-12-29T13:46:20.811Z",
                    "updated_at": "2020-12-29T13:46:20.908Z"
                },
                {
                    "id": 1392,
                    "name": "product-14-1-300x300.jpg",
                    "alternativeText": "",
                    "caption": "",
                    "width": 300,
                    "height": 300,
                    "formats": {},
                    "hash": "product_14_1_300x300_d6bee7d7b7",
                    "ext": ".jpg",
                    "mime": "image/jpeg",
                    "size": 7.6,
                    "url": "/db/uploads/product_14_1_300x300_d6bee7d7b7.jpg",
                    "previewUrl": null,
                    "provider": "local",
                    "provider_metadata": null,
                    "created_by": 4,
                    "updated_by": 4,
                    "created_at": "2020-12-29T13:46:20.839Z",
                    "updated_at": "2020-12-29T13:46:20.945Z"
                },
                {
                    "id": 1393,
                    "name": "product-14-3-300x300.jpg",
                    "alternativeText": "",
                    "caption": "",
                    "width": 300,
                    "height": 300,
                    "formats": {},
                    "hash": "product_14_3_300x300_008d1fffd4",
                    "ext": ".jpg",
                    "mime": "image/jpeg",
                    "size": 6.82,
                    "url": "/db/uploads/product_14_3_300x300_008d1fffd4.jpg",
                    "previewUrl": null,
                    "provider": "local",
                    "provider_metadata": null,
                    "created_by": 4,
                    "updated_by": 4,
                    "created_at": "2020-12-29T13:46:20.863Z",
                    "updated_at": "2020-12-29T13:46:20.978Z"
                }
            ],
            "category": [
                {
                    "id": 1,
                    "name": "Women",
                    "slug": "women",
                    "created_by": null,
                    "updated_by": 4,
                    "created_at": "2020-03-14T10:24:42.894Z",
                    "updated_at": "2020-12-24T01:56:51.418Z"
                },
                {
                    "id": 71,
                    "name": "Jackets & Vests",
                    "slug": "jackets-and-vests",
                    "created_by": 4,
                    "updated_by": 4,
                    "created_at": "2020-12-24T04:42:34.429Z",
                    "updated_at": "2020-12-24T04:42:34.446Z"
                }
            ],
            "size": [
                {
                    "id": 1,
                    "name": "Largi",
                    "slug": "L"
                }
            ],
            "color": [
                {
                    "id": 2,
                    "name": "Grey",
                    "slug": "grey"
                }
            ],
            "brands": [
                {
                    "id": 19,
                    "name": "Nike",
                    "slug": "nike",
                    "created_by": 4,
                    "updated_by": 4,
                    "created_at": "2020-12-24T00:43:24.892Z",
                    "updated_at": "2020-12-24T00:43:24.907Z"
                }
            ]
        },
        {
            "id": 270,
            "name": "Adidas Y-3 Yohji Yamamoto",
            "slug": "adidas-y-3-yohji-yamamoto",
            "short_desc": "Morbi purus libero, faucibus adipiscing, commodo quis, gravida id, est. Sed lectus. Praesent elementum hendrerit tortor. Sed semper lorem at felis. Vestibulum volutpat, lacus a ultrices sagittis, mi neque euismod dui, eu pulvinar nunc sapien ornare nisl. Phasellus pede arcu, dapibus eu, ",
            "price": 600,
            "sale_price": 239.99,
            "vendor": "demo24",
            "review": 2,
            "ratings": 3,
            "until": "2022-01-01",
            "stock": 100,
            "top": null,
            "featured": true,
            "new": null,
            "author": null,
            "sold": null,
            "created_by": {},
            "updated_by": {},
            "created_at": "2020-12-29T13:50:35.960Z",
            "updated_at": "2021-01-21T14:28:28.150Z",
            "variants": [],
            "pictures": [
                {
                    "id": 1394,
                    "name": "product-15-1.jpg",
                    "alternativeText": "",
                    "caption": "",
                    "width": 800,
                    "height": 800,
                    "formats": {},
                    "hash": "product_15_1_b349b4e462",
                    "ext": ".jpg",
                    "mime": "image/jpeg",
                    "size": 26.64,
                    "url": "/db/uploads/product_15_1_b349b4e462.jpg",
                    "previewUrl": null,
                    "provider": "local",
                    "provider_metadata": null,
                    "created_by": 4,
                    "updated_by": 4,
                    "created_at": "2020-12-29T13:48:06.520Z",
                    "updated_at": "2020-12-29T13:48:06.657Z"
                },
                {
                    "id": 1395,
                    "name": "product-15-2.jpg",
                    "alternativeText": "",
                    "caption": "",
                    "width": 800,
                    "height": 800,
                    "formats": {},
                    "hash": "product_15_2_0cd0d7ec61",
                    "ext": ".jpg",
                    "mime": "image/jpeg",
                    "size": 20.2,
                    "url": "/db/uploads/product_15_2_0cd0d7ec61.jpg",
                    "previewUrl": null,
                    "provider": "local",
                    "provider_metadata": null,
                    "created_by": 4,
                    "updated_by": 4,
                    "created_at": "2020-12-29T13:48:06.552Z",
                    "updated_at": "2020-12-29T13:48:06.692Z"
                },
                {
                    "id": 1396,
                    "name": "product-15-3.jpg",
                    "alternativeText": "",
                    "caption": "",
                    "width": 800,
                    "height": 800,
                    "formats": {},
                    "hash": "product_15_3_600256cc53",
                    "ext": ".jpg",
                    "mime": "image/jpeg",
                    "size": 16.45,
                    "url": "/db/uploads/product_15_3_600256cc53.jpg",
                    "previewUrl": null,
                    "provider": "local",
                    "provider_metadata": null,
                    "created_by": 4,
                    "updated_by": 4,
                    "created_at": "2020-12-29T13:48:06.581Z",
                    "updated_at": "2020-12-29T13:48:06.747Z"
                },
                {
                    "id": 1397,
                    "name": "product-15-4.jpg",
                    "alternativeText": "",
                    "caption": "",
                    "width": 800,
                    "height": 800,
                    "formats": {},
                    "hash": "product_15_4_7b184d845a",
                    "ext": ".jpg",
                    "mime": "image/jpeg",
                    "size": 23.94,
                    "url": "/db/uploads/product_15_4_7b184d845a.jpg",
                    "previewUrl": null,
                    "provider": "local",
                    "provider_metadata": null,
                    "created_by": 4,
                    "updated_by": 4,
                    "created_at": "2020-12-29T13:48:06.606Z",
                    "updated_at": "2020-12-29T13:48:06.794Z"
                }
            ],
            "sm_pictures": [
                {
                    "id": 1399,
                    "name": "product-15-1-300x300.jpg",
                    "alternativeText": "",
                    "caption": "",
                    "width": 300,
                    "height": 300,
                    "formats": {},
                    "hash": "product_15_1_300x300_b8f1c239b8",
                    "ext": ".jpg",
                    "mime": "image/jpeg",
                    "size": 7.26,
                    "url": "/db/uploads/product_15_1_300x300_b8f1c239b8.jpg",
                    "previewUrl": null,
                    "provider": "local",
                    "provider_metadata": null,
                    "created_by": 4,
                    "updated_by": 4,
                    "created_at": "2020-12-29T13:48:29.082Z",
                    "updated_at": "2020-12-29T13:48:29.209Z"
                },
                {
                    "id": 1398,
                    "name": "product-15-2-300x300.jpg",
                    "alternativeText": "",
                    "caption": "",
                    "width": 300,
                    "height": 300,
                    "formats": {},
                    "hash": "product_15_2_300x300_23d772a38c",
                    "ext": ".jpg",
                    "mime": "image/jpeg",
                    "size": 5.28,
                    "url": "/db/uploads/product_15_2_300x300_23d772a38c.jpg",
                    "previewUrl": null,
                    "provider": "local",
                    "provider_metadata": null,
                    "created_by": 4,
                    "updated_by": 4,
                    "created_at": "2020-12-29T13:48:29.052Z",
                    "updated_at": "2020-12-29T13:48:29.173Z"
                },
                {
                    "id": 1400,
                    "name": "product-15-3-300x300.jpg",
                    "alternativeText": "",
                    "caption": "",
                    "width": 300,
                    "height": 300,
                    "formats": {},
                    "hash": "product_15_3_300x300_1f213b5195",
                    "ext": ".jpg",
                    "mime": "image/jpeg",
                    "size": 4.05,
                    "url": "/db/uploads/product_15_3_300x300_1f213b5195.jpg",
                    "previewUrl": null,
                    "provider": "local",
                    "provider_metadata": null,
                    "created_by": 4,
                    "updated_by": 4,
                    "created_at": "2020-12-29T13:48:29.108Z",
                    "updated_at": "2020-12-29T13:48:29.245Z"
                },
                {
                    "id": 1401,
                    "name": "product-15-4-300x300.jpg",
                    "alternativeText": "",
                    "caption": "",
                    "width": 300,
                    "height": 300,
                    "formats": {},
                    "hash": "product_15_4_300x300_19fe8a3338",
                    "ext": ".jpg",
                    "mime": "image/jpeg",
                    "size": 6.04,
                    "url": "/db/uploads/product_15_4_300x300_19fe8a3338.jpg",
                    "previewUrl": null,
                    "provider": "local",
                    "provider_metadata": null,
                    "created_by": 4,
                    "updated_by": 4,
                    "created_at": "2020-12-29T13:48:29.131Z",
                    "updated_at": "2020-12-29T13:48:29.279Z"
                }
            ],
            "category": [
                {
                    "id": 2,
                    "name": "Men",
                    "slug": "men",
                    "created_by": null,
                    "updated_by": 4,
                    "created_at": "2020-03-14T10:25:21.611Z",
                    "updated_at": "2020-12-24T01:57:00.242Z"
                },
                {
                    "id": 3,
                    "name": "Shoes",
                    "slug": "shoes",
                    "created_by": null,
                    "updated_by": 4,
                    "created_at": "2020-03-14T10:25:39.408Z",
                    "updated_at": "2020-12-24T01:57:14.431Z"
                }
            ],
            "size": [
                {
                    "id": 1,
                    "name": "Largi",
                    "slug": "L"
                }
            ],
            "color": [
                {
                    "id": 2,
                    "name": "Grey",
                    "slug": "grey"
                }
            ],
            "brands": [
                {
                    "id": 19,
                    "name": "Nike",
                    "slug": "nike",
                    "created_by": 4,
                    "updated_by": 4,
                    "created_at": "2020-12-24T00:43:24.892Z",
                    "updated_at": "2020-12-24T00:43:24.907Z"
                }
            ]
        },
        {
            "id": 271,
            "name": "On Cloudflyer",
            "slug": "on-cloudflyer",
            "short_desc": "Morbi purus libero, faucibus adipiscing, commodo quis, gravida id, est. Sed lectus. Praesent elementum hendrerit tortor. Sed semper lorem at felis. Vestibulum volutpat, lacus a ultrices sagittis, mi neque euismod dui, eu pulvinar nunc sapien ornare nisl. Phasellus pede arcu, dapibus eu, ",
            "price": 127.99,
            "sale_price": null,
            "vendor": "demo24",
            "review": 2,
            "ratings": 3,
            "until": null,
            "stock": 100,
            "top": null,
            "featured": null,
            "new": null,
            "author": null,
            "sold": null,
            "created_by": {},
            "updated_by": {},
            "created_at": "2020-12-29T13:55:16.604Z",
            "updated_at": "2021-01-08T14:05:59.612Z",
            "variants": [],
            "pictures": [
                {
                    "id": 1405,
                    "name": "product-17-1.jpg",
                    "alternativeText": "",
                    "caption": "",
                    "width": 800,
                    "height": 800,
                    "formats": {},
                    "hash": "product_17_1_ab1b5ed1b6",
                    "ext": ".jpg",
                    "mime": "image/jpeg",
                    "size": 49.69,
                    "url": "/db/uploads/product_17_1_ab1b5ed1b6.jpg",
                    "previewUrl": null,
                    "provider": "local",
                    "provider_metadata": null,
                    "created_by": 4,
                    "updated_by": 4,
                    "created_at": "2020-12-29T13:53:57.979Z",
                    "updated_at": "2020-12-29T13:53:58.111Z"
                },
                {
                    "id": 1402,
                    "name": "product-17-2.jpg",
                    "alternativeText": "",
                    "caption": "",
                    "width": 800,
                    "height": 800,
                    "formats": {},
                    "hash": "product_17_2_352f9aeba4",
                    "ext": ".jpg",
                    "mime": "image/jpeg",
                    "size": 38.13,
                    "url": "/db/uploads/product_17_2_352f9aeba4.jpg",
                    "previewUrl": null,
                    "provider": "local",
                    "provider_metadata": null,
                    "created_by": 4,
                    "updated_by": 4,
                    "created_at": "2020-12-29T13:53:57.911Z",
                    "updated_at": "2020-12-29T13:53:58.015Z"
                },
                {
                    "id": 1403,
                    "name": "product-17-3.jpg",
                    "alternativeText": "",
                    "caption": "",
                    "width": 800,
                    "height": 800,
                    "formats": {},
                    "hash": "product_17_3_0df579ef1e",
                    "ext": ".jpg",
                    "mime": "image/jpeg",
                    "size": 20.34,
                    "url": "/db/uploads/product_17_3_0df579ef1e.jpg",
                    "previewUrl": null,
                    "provider": "local",
                    "provider_metadata": null,
                    "created_by": 4,
                    "updated_by": 4,
                    "created_at": "2020-12-29T13:53:57.939Z",
                    "updated_at": "2020-12-29T13:53:58.045Z"
                },
                {
                    "id": 1404,
                    "name": "product-17-4.jpg",
                    "alternativeText": "",
                    "caption": "",
                    "width": 800,
                    "height": 800,
                    "formats": {},
                    "hash": "product_17_4_bd96b7b768",
                    "ext": ".jpg",
                    "mime": "image/jpeg",
                    "size": 31.07,
                    "url": "/db/uploads/product_17_4_bd96b7b768.jpg",
                    "previewUrl": null,
                    "provider": "local",
                    "provider_metadata": null,
                    "created_by": 4,
                    "updated_by": 4,
                    "created_at": "2020-12-29T13:53:57.960Z",
                    "updated_at": "2020-12-29T13:53:58.078Z"
                }
            ],
            "sm_pictures": [
                {
                    "id": 1406,
                    "name": "product-17-1-300x408.jpg",
                    "alternativeText": "",
                    "caption": "",
                    "width": 300,
                    "height": 300,
                    "formats": {},
                    "hash": "product_17_1_300x408_625ccb6a0f",
                    "ext": ".jpg",
                    "mime": "image/jpeg",
                    "size": 10.12,
                    "url": "/db/uploads/product_17_1_300x408_625ccb6a0f.jpg",
                    "previewUrl": null,
                    "provider": "local",
                    "provider_metadata": null,
                    "created_by": 4,
                    "updated_by": 4,
                    "created_at": "2020-12-29T13:54:09.475Z",
                    "updated_at": "2020-12-29T13:54:09.595Z"
                },
                {
                    "id": 1407,
                    "name": "product-17-2-300x408.jpg",
                    "alternativeText": "",
                    "caption": "",
                    "width": 300,
                    "height": 300,
                    "formats": {},
                    "hash": "product_17_2_300x408_e2457e0025",
                    "ext": ".jpg",
                    "mime": "image/jpeg",
                    "size": 7.66,
                    "url": "/db/uploads/product_17_2_300x408_e2457e0025.jpg",
                    "previewUrl": null,
                    "provider": "local",
                    "provider_metadata": null,
                    "created_by": 4,
                    "updated_by": 4,
                    "created_at": "2020-12-29T13:54:09.496Z",
                    "updated_at": "2020-12-29T13:54:09.636Z"
                },
                {
                    "id": 1408,
                    "name": "product-17-3-300x408.jpg",
                    "alternativeText": "",
                    "caption": "",
                    "width": 300,
                    "height": 300,
                    "formats": {},
                    "hash": "product_17_3_300x408_308cd1e4e3",
                    "ext": ".jpg",
                    "mime": "image/jpeg",
                    "size": 4.27,
                    "url": "/db/uploads/product_17_3_300x408_308cd1e4e3.jpg",
                    "previewUrl": null,
                    "provider": "local",
                    "provider_metadata": null,
                    "created_by": 4,
                    "updated_by": 4,
                    "created_at": "2020-12-29T13:54:09.519Z",
                    "updated_at": "2020-12-29T13:54:09.674Z"
                },
                {
                    "id": 1409,
                    "name": "product-17-4-300x408.jpg",
                    "alternativeText": "",
                    "caption": "",
                    "width": 300,
                    "height": 300,
                    "formats": {},
                    "hash": "product_17_4_300x408_6bc7b415f8",
                    "ext": ".jpg",
                    "mime": "image/jpeg",
                    "size": 6.23,
                    "url": "/db/uploads/product_17_4_300x408_6bc7b415f8.jpg",
                    "previewUrl": null,
                    "provider": "local",
                    "provider_metadata": null,
                    "created_by": 4,
                    "updated_by": 4,
                    "created_at": "2020-12-29T13:54:09.545Z",
                    "updated_at": "2020-12-29T13:54:09.707Z"
                }
            ],
            "category": [
                {
                    "id": 2,
                    "name": "Men",
                    "slug": "men",
                    "created_by": null,
                    "updated_by": 4,
                    "created_at": "2020-03-14T10:25:21.611Z",
                    "updated_at": "2020-12-24T01:57:00.242Z"
                },
                {
                    "id": 3,
                    "name": "Shoes",
                    "slug": "shoes",
                    "created_by": null,
                    "updated_by": 4,
                    "created_at": "2020-03-14T10:25:39.408Z",
                    "updated_at": "2020-12-24T01:57:14.431Z"
                }
            ],
            "size": [
                {
                    "id": 1,
                    "name": "Largi",
                    "slug": "L"
                }
            ],
            "color": [
                {
                    "id": 2,
                    "name": "Grey",
                    "slug": "grey"
                }
            ],
            "brands": [
                {
                    "id": 19,
                    "name": "Nike",
                    "slug": "nike",
                    "created_by": 4,
                    "updated_by": 4,
                    "created_at": "2020-12-24T00:43:24.892Z",
                    "updated_at": "2020-12-24T00:43:24.907Z"
                }
            ]
        },
        {
            "id": 287,
            "name": "Troy Lee Designs A1 MIPS Bike Helmet",
            "slug": "troy-lee-designs-a1-mips-bike-helmet",
            "short_desc": "Sed egestas, ante et vulputate volutpat, eros pede semper est, vitae luctus metus libero eu augue. Morbi purus libero, faucibus adipiscing. Sed lectus.",
            "price": 150,
            "sale_price": 139,
            "vendor": "demo24",
            "review": 2,
            "ratings": 4,
            "until": "2022-01-01",
            "stock": 100,
            "top": true,
            "featured": true,
            "new": null,
            "author": null,
            "sold": null,
            "created_by": {},
            "updated_by": {},
            "created_at": "2020-12-30T06:59:43.097Z",
            "updated_at": "2021-01-08T14:08:34.532Z",
            "variants": [],
            "pictures": [
                {
                    "id": 1480,
                    "name": "product-7-1.jpg",
                    "alternativeText": "",
                    "caption": "",
                    "width": 800,
                    "height": 800,
                    "formats": {},
                    "hash": "product_7_1_fb79119d4f",
                    "ext": ".jpg",
                    "mime": "image/jpeg",
                    "size": 31.85,
                    "url": "/db/uploads/product_7_1_fb79119d4f.jpg",
                    "previewUrl": null,
                    "provider": "local",
                    "provider_metadata": null,
                    "created_by": 4,
                    "updated_by": 4,
                    "created_at": "2020-12-30T06:46:36.438Z",
                    "updated_at": "2020-12-30T06:46:36.550Z"
                },
                {
                    "id": 1481,
                    "name": "product-7-2.jpg",
                    "alternativeText": "",
                    "caption": "",
                    "width": 800,
                    "height": 800,
                    "formats": {},
                    "hash": "product_7_2_99196a3c24",
                    "ext": ".jpg",
                    "mime": "image/jpeg",
                    "size": 32.83,
                    "url": "/db/uploads/product_7_2_99196a3c24.jpg",
                    "previewUrl": null,
                    "provider": "local",
                    "provider_metadata": null,
                    "created_by": 4,
                    "updated_by": 4,
                    "created_at": "2020-12-30T06:46:36.471Z",
                    "updated_at": "2020-12-30T06:46:36.581Z"
                },
                {
                    "id": 1483,
                    "name": "product-7-3.jpg",
                    "alternativeText": "",
                    "caption": "",
                    "width": 800,
                    "height": 800,
                    "formats": {},
                    "hash": "product_7_3_0426e05624",
                    "ext": ".jpg",
                    "mime": "image/jpeg",
                    "size": 28.79,
                    "url": "/db/uploads/product_7_3_0426e05624.jpg",
                    "previewUrl": null,
                    "provider": "local",
                    "provider_metadata": null,
                    "created_by": 4,
                    "updated_by": 4,
                    "created_at": "2020-12-30T06:46:36.513Z",
                    "updated_at": "2020-12-30T06:46:36.658Z"
                },
                {
                    "id": 1482,
                    "name": "product-7-4.jpg",
                    "alternativeText": "",
                    "caption": "",
                    "width": 800,
                    "height": 800,
                    "formats": {},
                    "hash": "product_7_4_be1b430fb3",
                    "ext": ".jpg",
                    "mime": "image/jpeg",
                    "size": 17.84,
                    "url": "/db/uploads/product_7_4_be1b430fb3.jpg",
                    "previewUrl": null,
                    "provider": "local",
                    "provider_metadata": null,
                    "created_by": 4,
                    "updated_by": 4,
                    "created_at": "2020-12-30T06:46:36.492Z",
                    "updated_at": "2020-12-30T06:46:36.620Z"
                }
            ],
            "sm_pictures": [
                {
                    "id": 1484,
                    "name": "product-7-1-300x300.jpg",
                    "alternativeText": "",
                    "caption": "",
                    "width": 300,
                    "height": 300,
                    "formats": {},
                    "hash": "product_7_1_300x300_c748bebdc6",
                    "ext": ".jpg",
                    "mime": "image/jpeg",
                    "size": 7.91,
                    "url": "/db/uploads/product_7_1_300x300_c748bebdc6.jpg",
                    "previewUrl": null,
                    "provider": "local",
                    "provider_metadata": null,
                    "created_by": 4,
                    "updated_by": 4,
                    "created_at": "2020-12-30T06:46:46.128Z",
                    "updated_at": "2020-12-30T06:46:46.249Z"
                },
                {
                    "id": 1485,
                    "name": "product-7-2-300x300.jpg",
                    "alternativeText": "",
                    "caption": "",
                    "width": 300,
                    "height": 300,
                    "formats": {},
                    "hash": "product_7_2_300x300_cf8838f5d2",
                    "ext": ".jpg",
                    "mime": "image/jpeg",
                    "size": 8.57,
                    "url": "/db/uploads/product_7_2_300x300_cf8838f5d2.jpg",
                    "previewUrl": null,
                    "provider": "local",
                    "provider_metadata": null,
                    "created_by": 4,
                    "updated_by": 4,
                    "created_at": "2020-12-30T06:46:46.155Z",
                    "updated_at": "2020-12-30T06:46:46.286Z"
                },
                {
                    "id": 1486,
                    "name": "product-7-3-300x300.jpg",
                    "alternativeText": "",
                    "caption": "",
                    "width": 300,
                    "height": 300,
                    "formats": {},
                    "hash": "product_7_3_300x300_0ca774d7a5",
                    "ext": ".jpg",
                    "mime": "image/jpeg",
                    "size": 7.41,
                    "url": "/db/uploads/product_7_3_300x300_0ca774d7a5.jpg",
                    "previewUrl": null,
                    "provider": "local",
                    "provider_metadata": null,
                    "created_by": 4,
                    "updated_by": 4,
                    "created_at": "2020-12-30T06:46:46.181Z",
                    "updated_at": "2020-12-30T06:46:46.319Z"
                },
                {
                    "id": 1487,
                    "name": "product-7-4-300x300.jpg",
                    "alternativeText": "",
                    "caption": "",
                    "width": 300,
                    "height": 300,
                    "formats": {},
                    "hash": "product_7_4_300x300_25cf3a6a5b",
                    "ext": ".jpg",
                    "mime": "image/jpeg",
                    "size": 4.8,
                    "url": "/db/uploads/product_7_4_300x300_25cf3a6a5b.jpg",
                    "previewUrl": null,
                    "provider": "local",
                    "provider_metadata": null,
                    "created_by": 4,
                    "updated_by": 4,
                    "created_at": "2020-12-30T06:46:46.208Z",
                    "updated_at": "2020-12-30T06:46:46.351Z"
                }
            ],
            "category": [
                {
                    "id": 18,
                    "name": "Accessories",
                    "slug": "accessories",
                    "created_by": 4,
                    "updated_by": 4,
                    "created_at": "2020-12-24T03:48:30.273Z",
                    "updated_at": "2020-12-24T03:48:30.347Z"
                }
            ],
            "size": [
                {
                    "id": 1,
                    "name": "Largi",
                    "slug": "L"
                }
            ],
            "color": [
                {
                    "id": 2,
                    "name": "Grey",
                    "slug": "grey"
                }
            ],
            "brands": [
                {
                    "id": 1,
                    "name": "UGG",
                    "slug": "ugg",
                    "created_by": null,
                    "updated_by": 4,
                    "created_at": "2020-03-14T10:30:03.468Z",
                    "updated_at": "2020-12-24T00:41:33.614Z"
                },
                {
                    "id": 20,
                    "name": "F&F",
                    "slug": "fandf",
                    "created_by": 4,
                    "updated_by": 4,
                    "created_at": "2020-12-24T00:43:43.479Z",
                    "updated_at": "2020-12-24T00:43:43.499Z"
                }
            ]
        },
        {
            "id": 288,
            "name": "The North Face Fanorak 2.0",
            "slug": "the-north-face-fanorak-2.0",
            "short_desc": "Sed egestas, ante et vulputate volutpat, eros pede semper est, vitae luctus metus libero eu augue. Morbi purus libero, faucibus adipiscing. Sed lectus.",
            "price": 499.99,
            "sale_price": 419.99,
            "vendor": "demo24",
            "review": 2,
            "ratings": 5,
            "until": null,
            "stock": 100,
            "top": true,
            "featured": true,
            "new": null,
            "author": null,
            "sold": null,
            "created_by": {},
            "updated_by": {},
            "created_at": "2020-12-30T07:10:27.317Z",
            "updated_at": "2021-01-08T14:09:03.741Z",
            "variants": [],
            "pictures": [
                {
                    "id": 1490,
                    "name": "product-5-1.jpg",
                    "alternativeText": "",
                    "caption": "",
                    "width": 800,
                    "height": 800,
                    "formats": {},
                    "hash": "product_5_1_0013e5f18f",
                    "ext": ".jpg",
                    "mime": "image/jpeg",
                    "size": 24.31,
                    "url": "/db/uploads/product_5_1_0013e5f18f.jpg",
                    "previewUrl": null,
                    "provider": "local",
                    "provider_metadata": null,
                    "created_by": 4,
                    "updated_by": 4,
                    "created_at": "2020-12-30T07:06:32.749Z",
                    "updated_at": "2020-12-30T07:06:32.901Z"
                },
                {
                    "id": 1489,
                    "name": "product-5-2.jpg",
                    "alternativeText": "",
                    "caption": "",
                    "width": 800,
                    "height": 800,
                    "formats": {},
                    "hash": "product_5_2_af4e8d7932",
                    "ext": ".jpg",
                    "mime": "image/jpeg",
                    "size": 26.16,
                    "url": "/db/uploads/product_5_2_af4e8d7932.jpg",
                    "previewUrl": null,
                    "provider": "local",
                    "provider_metadata": null,
                    "created_by": 4,
                    "updated_by": 4,
                    "created_at": "2020-12-30T07:06:32.709Z",
                    "updated_at": "2020-12-30T07:06:32.861Z"
                },
                {
                    "id": 1488,
                    "name": "product-5-3.jpg",
                    "alternativeText": "",
                    "caption": "",
                    "width": 300,
                    "height": 300,
                    "formats": {},
                    "hash": "product_5_3_552ab6f5b1",
                    "ext": ".jpg",
                    "mime": "image/jpeg",
                    "size": 4.98,
                    "url": "/db/uploads/product_5_3_552ab6f5b1.jpg",
                    "previewUrl": null,
                    "provider": "local",
                    "provider_metadata": null,
                    "created_by": 4,
                    "updated_by": 4,
                    "created_at": "2020-12-30T07:06:32.637Z",
                    "updated_at": "2020-12-30T07:06:32.822Z"
                },
                {
                    "id": 1491,
                    "name": "product-5-4.jpg",
                    "alternativeText": "",
                    "caption": "",
                    "width": 800,
                    "height": 800,
                    "formats": {},
                    "hash": "product_5_4_c8aa5e664a",
                    "ext": ".jpg",
                    "mime": "image/jpeg",
                    "size": 45.8,
                    "url": "/db/uploads/product_5_4_c8aa5e664a.jpg",
                    "previewUrl": null,
                    "provider": "local",
                    "provider_metadata": null,
                    "created_by": 4,
                    "updated_by": 4,
                    "created_at": "2020-12-30T07:06:32.778Z",
                    "updated_at": "2020-12-30T07:06:32.942Z"
                }
            ],
            "sm_pictures": [
                {
                    "id": 1493,
                    "name": "product-5-1-300x300.jpg",
                    "alternativeText": "",
                    "caption": "",
                    "width": 300,
                    "height": 300,
                    "formats": {},
                    "hash": "product_5_1_300x300_0358eefa16",
                    "ext": ".jpg",
                    "mime": "image/jpeg",
                    "size": 6.11,
                    "url": "/db/uploads/product_5_1_300x300_0358eefa16.jpg",
                    "previewUrl": null,
                    "provider": "local",
                    "provider_metadata": null,
                    "created_by": 4,
                    "updated_by": 4,
                    "created_at": "2020-12-30T07:06:41.052Z",
                    "updated_at": "2020-12-30T07:06:41.190Z"
                },
                {
                    "id": 1492,
                    "name": "product-5-2-300x300.jpg",
                    "alternativeText": "",
                    "caption": "",
                    "width": 300,
                    "height": 300,
                    "formats": {},
                    "hash": "product_5_2_300x300_f8fdeb8915",
                    "ext": ".jpg",
                    "mime": "image/jpeg",
                    "size": 7.11,
                    "url": "/db/uploads/product_5_2_300x300_f8fdeb8915.jpg",
                    "previewUrl": null,
                    "provider": "local",
                    "provider_metadata": null,
                    "created_by": 4,
                    "updated_by": 4,
                    "created_at": "2020-12-30T07:06:41.020Z",
                    "updated_at": "2020-12-30T07:06:41.129Z"
                },
                {
                    "id": 1495,
                    "name": "product-5-3-300x300.jpg",
                    "alternativeText": "",
                    "caption": "",
                    "width": 800,
                    "height": 800,
                    "formats": {},
                    "hash": "product_5_3_300x300_65d4e4b3bd",
                    "ext": ".jpg",
                    "mime": "image/jpeg",
                    "size": 18.05,
                    "url": "/db/uploads/product_5_3_300x300_65d4e4b3bd.jpg",
                    "previewUrl": null,
                    "provider": "local",
                    "provider_metadata": null,
                    "created_by": 4,
                    "updated_by": 4,
                    "created_at": "2020-12-30T07:06:41.153Z",
                    "updated_at": "2020-12-30T07:06:41.266Z"
                },
                {
                    "id": 1494,
                    "name": "product-5-4-300x300.jpg",
                    "alternativeText": "",
                    "caption": "",
                    "width": 300,
                    "height": 300,
                    "formats": {},
                    "hash": "product_5_4_300x300_42215ff2f3",
                    "ext": ".jpg",
                    "mime": "image/jpeg",
                    "size": 12.53,
                    "url": "/db/uploads/product_5_4_300x300_42215ff2f3.jpg",
                    "previewUrl": null,
                    "provider": "local",
                    "provider_metadata": null,
                    "created_by": 4,
                    "updated_by": 4,
                    "created_at": "2020-12-30T07:06:41.087Z",
                    "updated_at": "2020-12-30T07:06:41.231Z"
                }
            ],
            "category": [
                {
                    "id": 79,
                    "name": "Jackets",
                    "slug": "jackets",
                    "created_by": 4,
                    "updated_by": 4,
                    "created_at": "2020-12-24T04:46:07.880Z",
                    "updated_at": "2020-12-24T04:46:07.894Z"
                }
            ],
            "size": [
                {
                    "id": 1,
                    "name": "Largi",
                    "slug": "L"
                }
            ],
            "color": [
                {
                    "id": 2,
                    "name": "Grey",
                    "slug": "grey"
                }
            ],
            "brands": [
                {
                    "id": 22,
                    "name": "New Balance",
                    "slug": "new-balance",
                    "created_by": 4,
                    "updated_by": 4,
                    "created_at": "2020-12-24T00:44:31.990Z",
                    "updated_at": "2020-12-24T00:44:32.007Z"
                }
            ]
        }
    ]
}